genanki/__init__.py
genanki/apkg_col.py
genanki/apkg_schema.py
genanki/card.py
genanki/db.py
genanki/deck.py
genanki/model.py
genanki/note.py
genanki/package.py
genanki/util.py
genanki/version.py
genanki_marccarre-0.6.4.dist-info/LICENSE.txt
genanki_marccarre-0.6.4.dist-info/METADATA
genanki_marccarre-0.6.4.dist-info/WHEEL
genanki_marccarre-0.6.4.dist-info/top_level.txt
genanki_marccarre-0.6.4.dist-info/RECORD
