Metadata-Version: 2.1
Name: genanki-marccarre
Version: 0.6.4
Summary: Generate Anki decks programmatically (fork from http://github.com/kerrickstaley/genanki)
Home-page: http://github.com/marccarre/genanki
Author: Marc Carré (fork maintainer), Kerrick Staley (original author)
Author-email: carre.marc@gmail.com
License: MIT
Keywords: anki,flashcards,memorization
Platform: UNKNOWN
Requires-Dist: cached-property
Requires-Dist: frozendict
Requires-Dist: pystache
Requires-Dist: pyyaml
